setup.py
canalweb/__init__.py
canalweb/cli.py
canalweb/flvread.py
canalweb/test_vod.py
canalweb/test_xspf.py
canalweb/vod.py
canalweb/xspf.py
canalweb.egg-info/PKG-INFO
canalweb.egg-info/SOURCES.txt
canalweb.egg-info/dependency_links.txt
canalweb.egg-info/entry_points.txt
canalweb.egg-info/top_level.txt