Metadata-Version: 1.0
Name: canalweb
Version: 0.5
Summary: Offline viewing of Canal+ shows
Home-page: http://github.com/chbug/canalweb
Author: Frederic Gobry
Author-email: gobry@yorglu.net
License: GPLv3
Platform: UNKNOWN
